cobcom_talon-0.3.0.post0.data/scripts/talon
talon/__init__.py
talon/core.py
talon/fast.py
talon/opencl.py
talon/optimization.py
talon/utils.py
talon/voxelization.py
talon/cli/__init__.py
talon/cli/parser.py
talon/cli/utils.py
cobcom_talon-0.3.0.post0.dist-info/LICENSE
cobcom_talon-0.3.0.post0.dist-info/METADATA
cobcom_talon-0.3.0.post0.dist-info/WHEEL
cobcom_talon-0.3.0.post0.dist-info/top_level.txt
cobcom_talon-0.3.0.post0.dist-info/RECORD
