Metadata-Version: 2.1
Name: cobcom-talon
Version: 0.3.0.post0
Summary: A Python package that implements Tractograms As Linear Operators in Neuroimaging
Home-page: https://gitlab.inria.fr/cobcom/talon
Author: Samuel Deslauriers-Gauthier, Matteo Frigo, Mauro Zucchelli
License: UNKNOWN
Project-URL: Source, https://gitlab.inria.fr/cobcom/talon
Project-URL: Bug Reports, https://gitlab.inria.fr/cobcom/talon/issues
Project-URL: Documentation, https://cobcom-talon.readthedocs.io
Platform: UNKNOWN
Classifier: Development Status :: 4 - Beta
Classifier: Intended Audience :: Science/Research
Classifier: License :: OSI Approved :: MIT License
Classifier: Programming Language :: Python :: 3
Classifier: Topic :: Scientific/Engineering :: Medical Science Apps.
Requires-Python: >=3
Requires-Dist: nibabel
Requires-Dist: numpy
Requires-Dist: pyunlocbox
Requires-Dist: scipy
Provides-Extra: opencl
Requires-Dist: pyopencl ; extra == 'opencl'
Requires-Dist: pocl ; extra == 'opencl'
